brickmapper/__init__.py
brickmapper-0.1.3.dist-info/LICENSE
brickmapper-0.1.3.dist-info/METADATA
brickmapper-0.1.3.dist-info/WHEEL
brickmapper-0.1.3.dist-info/RECORD
