Metadata-Version: 2.1
Name: brickmapper
Version: 0.1.3
Summary: Use LLM embeddings to create mappings between the Brick ontology and external vocabularies
License: BSD-3-Clause
Author: Gabe Fierro
Author-email: gtfierro@mines.edu
Requires-Python: >=3.9,<3.12
Classifier: License :: OSI Approved :: BSD License
Classifier: Programming Language :: Python :: 3
Classifier: Programming Language :: Python :: 3.9
Classifier: Programming Language :: Python :: 3.10
Classifier: Programming Language :: Python :: 3.11
Requires-Dist: fnvhash (>=0.1.0,<0.2.0)
Requires-Dist: loguru (>=0.7.0,<0.8.0)
Requires-Dist: openai (>=0.27.8,<0.28.0)
Requires-Dist: rdflib (>=7.0.0,<8.0.0)
Requires-Dist: tqdm (>=4.65.0,<5.0.0)
Requires-Dist: usearch (>=1.1.1,<2.0.0)
